dot2bgraph/__init__.py
dot2bgraph/__main__.py
dot2bgraph/image.py
dot2bgraph/locations.py
dot2bgraph/main.py
dot2bgraph/converter/__init__.py
dot2bgraph/converter/directed.py
dot2bgraph/converter/grid.py
dot2bgraph/converter/node.py
dot2bgraph/converter/pack.py
dot2bgraph/utils/__init__.py
dot2bgraph/utils/color.py
dot2bgraph/utils/spinner.py
dot2bgraph-0.1.2.dist-info/LICENSE
dot2bgraph-0.1.2.dist-info/METADATA
dot2bgraph-0.1.2.dist-info/WHEEL
dot2bgraph-0.1.2.dist-info/entry_points.txt
dot2bgraph-0.1.2.dist-info/top_level.txt
dot2bgraph-0.1.2.dist-info/RECORD
