Metadata-Version: 2.1
Name: dot2bgraph
Version: 0.1.2
Summary: A CLI to convert dot files to bgraph format for visualization.
Author-email: Vasily Rudchenko <vasily.rudchenko.dev@gmail.com>
License: 
Project-URL: Homepage, https://github.com/vasilyrud/dot2bgraph
Keywords: graph,visualization,dot,bgraph,command,line,interface,cli,tool,convert
Classifier: Development Status :: 4 - Beta
Classifier: Intended Audience :: End Users/Desktop
Classifier: Intended Audience :: Developers
Classifier: Intended Audience :: Science/Research
Classifier: Topic :: Scientific/Engineering :: Visualization
Classifier: Topic :: Scientific/Engineering :: Information Analysis
Classifier: License :: OSI Approved :: Apache Software License
Classifier: Programming Language :: Python
Classifier: Programming Language :: Python :: 3
Classifier: Programming Language :: Python :: 3.7
Classifier: Programming Language :: Python :: 3.8
Classifier: Programming Language :: Python :: 3.9
License-File: LICENSE
Requires-Dist: pygraphviz
Requires-Dist: rectpack
Requires-Dist: Pillow
Requires-Dist: tqdm
Requires-Dist: yaspin
Provides-Extra: dev
Requires-Dist: pytest ; extra == 'dev'
Requires-Dist: pytest-cov ; extra == 'dev'
Requires-Dist: mypy ; extra == 'dev'
Requires-Dist: build ; extra == 'dev'
Requires-Dist: twine ; extra == 'dev'
